<?xml version="1.0" encoding="UTF-8"?>
<Entities
 majorVersion="9"
 minorVersion="1"
 universal="password">
    <StyleDefinitions>
        <StyleDefinition
         aspect.isThemeObject="true"
         description="DefaultPanelStyle for Panel in Theme: Thingworx"
         documentationContent=""
         homeMashup=""
         name="freshfoodspanelbgd"
         projectName="FreshFoodsMonitoringProject"
         tags="">
            <avatar></avatar>
            <DesignTimePermissions>
                <Create></Create>
                <Read></Read>
                <Update></Update>
                <Delete></Delete>
                <Metadata></Metadata>
            </DesignTimePermissions>
            <RunTimePermissions></RunTimePermissions>
            <VisibilityPermissions>
                <Visibility></Visibility>
            </VisibilityPermissions>
            <ConfigurationTableDefinitions></ConfigurationTableDefinitions>
            <ConfigurationTables></ConfigurationTables>
            <content>
            <![CDATA[
            {
              "backgroundColor" : "rgba(28,46,74,1)",
              "displayString" : "",
              "fontEmphasisBold" : false,
              "fontEmphasisItalic" : false,
              "fontEmphasisUnderline" : false,
              "foregroundColor" : "rgba(255,255,255,1)",
              "image" : "",
              "lineColor" : "rgba(255,255,255,1)",
              "lineStyle" : "solid",
              "lineThickness" : "0",
              "secondaryBackgroundColor" : "",
              "textSize" : "normal"
            }
            ]]>
            </content>
        </StyleDefinition>
    </StyleDefinitions>
</Entities>
